cp_template/__init__.py
cp_template/version.py
cp_template-0.3.0.dist-info/entry_points.txt
cp_template-0.3.0.dist-info/WHEEL
cp_template-0.3.0.dist-info/METADATA
cp_template-0.3.0.dist-info/RECORD
