Metadata-Version: 2.1
Name: cp-template
Version: 0.3.0
Summary: A tool to copy templated directories
Home-page: https://github.com/breuleux/cp-template
License: MIT
Author: Olivier Breuleux
Author-email: breuleux@gmail.com
Requires-Python: >=3.7,<4.0
Classifier: License :: OSI Approved :: MIT License
Classifier: Programming Language :: Python :: 3
Classifier: Programming Language :: Python :: 3.10
Classifier: Programming Language :: Python :: 3.7
Classifier: Programming Language :: Python :: 3.8
Classifier: Programming Language :: Python :: 3.9
Requires-Dist: coleo (>=0.3.0,<0.4.0)
Requires-Dist: pystache (>=0.6.0,<0.7.0)
Project-URL: Repository, https://github.com/breuleux/cp-template
